genoptimizer/__init__.py
genoptimizer/genoptimizer.py
genoptimizer/config/__init__.py
genoptimizer/config/default_parameters.py
genoptimizer/core/__init__.py
genoptimizer/core/population.py
genoptimizer/operators/__init__.py
genoptimizer/operators/crossover.py
genoptimizer/operators/fitness.py
genoptimizer/operators/mutation.py
genoptimizer/operators/selection.py
GenOptimizer-0.5.dist-info/METADATA
GenOptimizer-0.5.dist-info/WHEEL
GenOptimizer-0.5.dist-info/top_level.txt
GenOptimizer-0.5.dist-info/RECORD
