Metadata-Version: 2.1
Name: GenOptimizer
Version: 0.5
Summary: A simple genetic algorithm optimization library
Classifier: Programming Language :: Python :: 3
Classifier: License :: OSI Approved :: MIT License
Classifier: Operating System :: OS Independent
Requires-Python: >=3.6
Requires-Dist: numpy>=1.18.0
Requires-Dist: matplotlib>=3.0.0
